tdda/CHANGES.py
tdda/__init__.py
tdda/debug.py
tdda/examples.py
tdda/test_tdda.py
tdda/testconfig.py
tdda/testtdda.py
tdda/utils.py
tdda/version.py
tdda/writabletestcase.py
tdda/constraints/__init__.py
tdda/constraints/base.py
tdda/constraints/baseconstraints.py
tdda/constraints/console.py
tdda/constraints/examples.py
tdda/constraints/extension.py
tdda/constraints/flags.py
tdda/constraints/pdconstraints.py
tdda/constraints/pddiscover.py
tdda/constraints/pdverify.py
tdda/constraints/tdda_json_file_format.md
tdda/constraints/testbase.py
tdda/constraints/testconstraints.py
tdda/constraints/db/__init__.py
tdda/constraints/db/constraints.py
tdda/constraints/db/detect.py
tdda/constraints/db/discover.py
tdda/constraints/db/drivers.py
tdda/constraints/db/extension.py
tdda/constraints/db/testdbconstraints.py
tdda/constraints/db/verify.py
tdda/constraints/db/init/mysql-create-elements.sql
tdda/constraints/db/init/postgres-create-elements.sql
tdda/constraints/examples/README.md
tdda/constraints/examples/accounts.zip
tdda/constraints/examples/accounts_detect_25k_against_1k.py
tdda/constraints/examples/accounts_discover_1k.py
tdda/constraints/examples/accounts_verify_1k.py
tdda/constraints/examples/accounts_verify_25k.py
tdda/constraints/examples/accounts_verify_25k_against_1k.py
tdda/constraints/examples/accounts_verify_25k_against_1k_parquet.py
tdda/constraints/examples/accounts_verify_25k_to_frame.py
tdda/constraints/examples/elements_detect_118_against_92.py
tdda/constraints/examples/elements_discover_92.py
tdda/constraints/examples/elements_verify_118.py
tdda/constraints/examples/elements_verify_118_against_92.py
tdda/constraints/examples/elements_verify_118_against_92_parquet.py
tdda/constraints/examples/elements_verify_92.py
tdda/constraints/examples/files_extension.py
tdda/constraints/examples/simple_discovery.py
tdda/constraints/examples/simple_verification.py
tdda/constraints/examples/simple_verify_fail.py
tdda/constraints/examples/simple_verify_pass.py
tdda-2.2.17.dist-info/LICENSE.txt
tdda-2.2.17.dist-info/METADATA
tdda-2.2.17.dist-info/WHEEL
tdda-2.2.17.dist-info/entry_points.txt
tdda-2.2.17.dist-info/top_level.txt
tdda-2.2.17.dist-info/RECORD
