Metadata-Version: 2.2
Name: tdda
Version: 2.2.17
Home-page: http://www.stochasticsolutions.com
Download-URL: https://github.com/tdda/tdda
Author: Simon Brown
Author-email: Nick Radcliffe <njr@stochasticsolutions.com>
License: MIT
Keywords: tdda constraint referencetest rexpy
Requires-Python: >=3.8
License-File: LICENSE.txt
Requires-Dist: numpy>=1.20.3
Requires-Dist: pandas>=1.5.2
Requires-Dist: pyarrow>=15.0
Requires-Dist: pyyaml>=6.0
Requires-Dist: pytest
Requires-Dist: chardet>=5.2
Requires-Dist: rich>=13.3
Dynamic: description
Dynamic: download-url
Dynamic: home-page
Dynamic: keywords
Dynamic: license
Dynamic: requires-dist
